parallel_execute-2.0.3.dist-info/licenses/LICENSE
pexecute/__init__.py
pexecute/log_adapter.py
pexecute/process/__init__.py
pexecute/process/loom.py
pexecute/thread/__init__.py
pexecute/thread/loom.py
parallel_execute-2.0.3.dist-info/METADATA
parallel_execute-2.0.3.dist-info/WHEEL
parallel_execute-2.0.3.dist-info/top_level.txt
parallel_execute-2.0.3.dist-info/RECORD
